soco_mrc/__init__.py
soco_mrc/cloud_bucket.py
soco_mrc/config.py
soco_mrc/mrc_base.py
soco_mrc/mrc_model.py
soco_mrc/server.py
soco_mrc/util.py
soco_mrc/model/__init__.py
soco_mrc/model/bert_model.py
soco_mrc-0.0.9.dist-info/LICENSE
soco_mrc-0.0.9.dist-info/METADATA
soco_mrc-0.0.9.dist-info/WHEEL
soco_mrc-0.0.9.dist-info/top_level.txt
soco_mrc-0.0.9.dist-info/RECORD
