Metadata-Version: 2.1
Name: soco-mrc
Version: 0.0.9
Summary: Neural machine reading comprehension models
Home-page: https://www.soco.ai
Author: tianchez
License: UNKNOWN
Platform: UNKNOWN
Classifier: Programming Language :: Python :: 3
Classifier: License :: Free for non-commercial use
Classifier: Operating System :: OS Independent
Requires-Dist: aiofiles (>=0.4.0)
Requires-Dist: aiohttp (>=3.5.4)
Requires-Dist: asyncio (>=3.4.3)
Requires-Dist: torch (>=1.2.0)
Requires-Dist: numpy (>=1.16.3)
Requires-Dist: starlette (>=0.12.0)
Requires-Dist: uvicorn (>=0.7.1)
Requires-Dist: python-multipart (>=0.0.5)
Requires-Dist: transformers (==2.11.0)
Requires-Dist: soco-device (==0.0.5.2)
Requires-Dist: boto3 (>=1.9.134)
Requires-Dist: oss2 (>=2.6.1)
